djaodjin_saas-1.1.6.dist-info/licenses/LICENSE.txt
saas/__init__.py
saas/admin.py
saas/cart.py
saas/compat.py
saas/decorators.py
saas/docs.py
saas/extras.py
saas/filters.py
saas/forms.py
saas/helpers.py
saas/humanize.py
saas/ledger.py
saas/mixins.py
saas/models.py
saas/pagination.py
saas/renewals.py
saas/settings.py
saas/signals.py
saas/tests.py
saas/utils.py
saas/api/__init__.py
saas/api/accounts.py
saas/api/agreements.py
saas/api/backend.py
saas/api/balances.py
saas/api/billing.py
saas/api/charges.py
saas/api/coupons.py
saas/api/federations.py
saas/api/metrics.py
saas/api/organizations.py
saas/api/plans.py
saas/api/renewals.py
saas/api/roles.py
saas/api/serializers.py
saas/api/serializers_overrides.py
saas/api/subscriptions.py
saas/api/transactions.py
saas/api/users.py
saas/backends/__init__.py
saas/backends/fake_processor.py
saas/backends/flutterwave_processor.py
saas/backends/razorpay_processor.py
saas/backends/stripe_processor/__init__.py
saas/backends/stripe_processor/base.py
saas/backends/stripe_processor/views.py
saas/backends/stripe_processor/urls/__init__.py
saas/backends/stripe_processor/urls/api.py
saas/backends/stripe_processor/urls/views.py
saas/backends/urls/__init__.py
saas/backends/urls/api.py
saas/backends/urls/views.py
saas/management/__init__.py
saas/management/commands/__init__.py
saas/management/commands/compile_stats.py
saas/management/commands/delete_organization.py
saas/management/commands/delete_processor_customers.py
saas/management/commands/ledger.py
saas/management/commands/reconcile_with_processor.py
saas/management/commands/renewals.py
saas/management/commands/report_weekly_revenue.py
saas/management/commands/send_invites.py
saas/metrics/__init__.py
saas/metrics/base.py
saas/metrics/subscriptions.py
saas/metrics/transactions.py
saas/migrations/0001_initial.py
saas/migrations/0002_auto_20161126_2248.py
saas/migrations/0003_balanceline_is_positive.py
saas/migrations/0004_auto_20161221_1944.py
saas/migrations/0005_role_extra.py
saas/migrations/0006_0_3_0.py
saas/migrations/0007_0_3_3.py
djaodjin_saas-1.1.6.dist-info/METADATA
djaodjin_saas-1.1.6.dist-info/WHEEL
djaodjin_saas-1.1.6.dist-info/top_level.txt
djaodjin_saas-1.1.6.dist-info/RECORD
