Metadata-Version: 2.4
Name: djaodjin-saas
Version: 1.1.6
Summary: Django application for software-as-service and subscription businesses
Author-email: The DjaoDjin Team <help@djaodjin.com>
Maintainer-email: The DjaoDjin Team <help@djaodjin.com>
License: BSD-2-Clause
Project-URL: repository, https://github.com/djaodjin/djaodjin-saas
Project-URL: documentation, https://djaodjin-saas.readthedocs.io/
Project-URL: changelog, https://github.com/djaodjin/djaodjin-saas/changelog
Keywords: django,stripe,saas,subscriptions,razorpay,plans
Classifier: Framework :: Django
Classifier: Environment :: Web Environment
Classifier: Programming Language :: Python
Classifier: License :: OSI Approved :: BSD License
Requires-Python: >=3.7
License-File: LICENSE.txt
Requires-Dist: Django>=1.11
Requires-Dist: django-countries>=2.1.2
Requires-Dist: django-localflavor>=1.0
Requires-Dist: django-phonenumber-field>=2.4.0
Requires-Dist: djangorestframework>=3.3.1
Requires-Dist: Markdown>=2.4
Requires-Dist: phonenumbers>=8.12.6
Requires-Dist: python-dateutil>=2.2
Requires-Dist: stripe==12.5.1
Requires-Dist: razorpay>=0.2.0
Dynamic: license-file
